{
  "hash": "b3ce3281",
  "configHash": "3270b116",
  "lockfileHash": "f536256a",
  "browserHash": "6c966fb5",
  "optimized": {
    "markmap-lib": {
      "src": "../../../../node_modules/markmap-lib/dist/browser/index.mjs",
      "file": "markmap-lib.js",
      "fileHash": "77f11a5e",
      "needsInterop": false
    },
    "markmap-toolbar": {
      "src": "../../../../node_modules/markmap-toolbar/dist/index.mjs",
      "file": "markmap-toolbar.js",
      "fileHash": "96ccb83e",
      "needsInterop": false
    },
    "markmap-view": {
      "src": "../../../../node_modules/markmap-view/dist/index.js",
      "file": "markmap-view.js",
      "fileHash": "cdb04a07",
      "needsInterop": false
    },
    "shiki/core": {
      "src": "../../../../node_modules/shiki/dist/core.mjs",
      "file": "shiki_core.js",
      "fileHash": "8f55025a",
      "needsInterop": false
    },
    "shiki/wasm": {
      "src": "../../../../node_modules/shiki/dist/wasm.mjs",
      "file": "shiki_wasm.js",
      "fileHash": "6201c8e2",
      "needsInterop": false
    },
    "shiki/engine/oniguruma": {
      "src": "../../../../node_modules/shiki/dist/engine-oniguruma.mjs",
      "file": "shiki_engine_oniguruma.js",
      "fileHash": "d9b33090",
      "needsInterop": false
    },
    "artplayer": {
      "src": "../../../../node_modules/artplayer/dist/artplayer.js",
      "file": "artplayer.js",
      "fileHash": "01923138",
      "needsInterop": true
    },
    "mark.js/src/vanilla.js": {
      "src": "../../../../node_modules/mark.js/src/vanilla.js",
      "file": "mark__js_src_vanilla__js.js",
      "fileHash": "be49ad8c",
      "needsInterop": false
    },
    "@vueuse/integrations/useFocusTrap": {
      "src": "../../../../node_modules/@vueuse/integrations/useFocusTrap.mjs",
      "file": "@vueuse_integrations_useFocusTrap.js",
      "fileHash": "d428ffc1",
      "needsInterop": false
    },
    "minisearch": {
      "src": "../../../../node_modules/minisearch/dist/es/index.js",
      "file": "minisearch.js",
      "fileHash": "3903fb12",
      "needsInterop": false
    },
    "@vueuse/core": {
      "src": "../../../../node_modules/@vueuse/core/index.mjs",
      "file": "@vueuse_core.js",
      "fileHash": "aa5c7b7a",
      "needsInterop": false
    },
    "bcrypt-ts/browser": {
      "src": "../../../../node_modules/bcrypt-ts/dist/browser.mjs",
      "file": "bcrypt-ts_browser.js",
      "fileHash": "38bc11c6",
      "needsInterop": false
    },
    "@vuepress/helper/client": {
      "src": "../../../../node_modules/@vuepress/helper/lib/client/index.js",
      "file": "@vuepress_helper_client.js",
      "fileHash": "ad49ec2f",
      "needsInterop": false
    },
    "@iconify/vue": {
      "src": "../../../../node_modules/@iconify/vue/dist/iconify.mjs",
      "file": "@iconify_vue.js",
      "fileHash": "f3b3d3aa",
      "needsInterop": false
    },
    "@iconify/vue/offline": {
      "src": "../../../../node_modules/@iconify/vue/dist/offline.mjs",
      "file": "@iconify_vue_offline.js",
      "fileHash": "53759f4f",
      "needsInterop": false
    },
    "@vuepress/plugin-git/client": {
      "src": "../../../../node_modules/@vuepress/plugin-git/lib/client/index.js",
      "file": "@vuepress_plugin-git_client.js",
      "fileHash": "58aee5e9",
      "needsInterop": false
    },
    "@vue/devtools-api": {
      "src": "../../../../node_modules/@vue/devtools-api/dist/index.js",
      "file": "@vue_devtools-api.js",
      "fileHash": "861680e7",
      "needsInterop": false
    },
    "@vuepress/shared": {
      "src": "../../../../node_modules/@vuepress/shared/dist/index.js",
      "file": "@vuepress_shared.js",
      "fileHash": "7981f3ea",
      "needsInterop": false
    },
    "vue": {
      "src": "../../../../node_modules/vue/dist/vue.runtime.esm-bundler.js",
      "file": "vue.js",
      "fileHash": "f531e628",
      "needsInterop": false
    },
    "vue-router": {
      "src": "../../../../node_modules/vue-router/dist/vue-router.esm-bundler.js",
      "file": "vue-router.js",
      "fileHash": "5928fdf5",
      "needsInterop": false
    }
  },
  "chunks": {
    "chunk-GOIEEV6W": {
      "file": "chunk-GOIEEV6W.js"
    },
    "chunk-66T3UYFC": {
      "file": "chunk-66T3UYFC.js"
    },
    "chunk-LW4I4DCF": {
      "file": "chunk-LW4I4DCF.js"
    },
    "chunk-2TW2Q2U4": {
      "file": "chunk-2TW2Q2U4.js"
    },
    "chunk-DC5AMYBS": {
      "file": "chunk-DC5AMYBS.js"
    }
  }
}